README.md
setup.cfg
setup.py
incapsula/__init__.py
incapsula/addSite.py
incapsula/com_error.py
incapsula/getAdvancedCachingOptions.py
incapsula/getCacheMode.py
incapsula/getDomainApproverEmail.py
incapsula/getReport.py
incapsula/getRules.py
incapsula/getSiteStatus.py
incapsula/getSites.py
incapsula/getSubAccounts.py
incapsula/getValidate.py
incapsula/getVisits.py
incapsula/listSites.py
incapsula/modCacheLevel.py
incapsula/modCachingRule.py
incapsula/modCustomCert.py
incapsula/modSiteACL.py
incapsula/modSiteLogLevel.py
incapsula/modSiteSecurityConfig.py
incapsula/modTLS.py
incapsula/redirectHTTP.py
incapsula/sendRequest.py
incapsula.egg-info/PKG-INFO
incapsula.egg-info/SOURCES.txt
incapsula.egg-info/dependency_links.txt
incapsula.egg-info/requires.txt
incapsula.egg-info/top_level.txt