Metadata-Version: 1.1
Name: incapsula
Version: 0.7.5
Summary: A python module for using the Incapsula API
Home-page: https://github.com/john-lowry/pyincapsula
Author: John Lowry
Author-email: johnlowry@gmail.com
License: GPL v2.0
Keywords: WAF Incapsula
Platform: UNKNOWN
Classifier: Development Status :: 2 - Pre-Alpha
Classifier: License :: OSI Approved :: GNU General Public License v2 (GPLv2)
Classifier: Programming Language :: Python :: 2
Classifier: Programming Language :: Python :: 3
Classifier: Topic :: Internet :: Proxy Servers
Classifier: Topic :: Security
